instantcli.py
instantcli-1.0.4.dist-info/METADATA
instantcli-1.0.4.dist-info/WHEEL
instantcli-1.0.4.dist-info/top_level.txt
instantcli-1.0.4.dist-info/RECORD
