Metadata-Version: 2.1
Name: instantcli
Version: 1.0.4
Requires-Dist: Click
